{
	"sprites":[
		{
			"id":"A","width":16,"height":10,
			"x":16,"y":60,
			"graphicsX":{"_placeholder":"playerGraphicsX"},
			"graphicsY":{"_placeholder":"playerGraphicsY"},
			"animations":[{"frames":[0,1],"speed":2}],
			"animation":0,
			"zIndex":1
		},
		{
			"id":"B","width":16,"height":8,
			"speedX":{"_placeholder":"scrollSpeed"},
			"flags":"C",
			"y":128,
			"graphicsX":{"_placeholder":"blockGraphicsX"},
			"graphicsY":{"_placeholder":"blockGraphicsY"},
			"backgroundColor":{"_placeholder":"blockBackgroundColor"},
			"zIndex":1
		},
		{
			"id":"C","width":16,"height":16,
			"flags":"BC",
			"speedX":{"_placeholder":"scrollSpeed"},
			"x":160,"y":0,
			"graphicsX":{"_placeholder":"wallGraphicsX"},
			"graphicsY":{"_placeholder":"wallGraphicsY"},
			"backgroundColor":{"_placeholder":"wallBackgroundColor"},
			"zIndex":1
		},
		{
			"id":"D","width":16,
			"height":{"_placeholder":"holeHeight"},"x":160
		},
		{
			"id":"E","width":16,"height":16,
			"flags":"B",
			"speedX":{"_placeholder":"scrollSpeed"},
			"graphicsX":{"_placeholder":"bonusGraphicsX"},
			"graphicsY":{"_placeholder":"bonusGraphicsY"},
			"zIndex":1,
			"animations":[{"frames":[0,1],"speed":4}],"animation":0
		},
		{
			"id":"F","width":16,"height":8,
			"x":-16,
			"speedX":{"_placeholder":"cloudSpeed"},
			"graphicsX":{"_placeholder":"cloudGraphicsX"},
			"graphicsY":{"_placeholder":"cloudGraphicsY"}
		},
		{
			"id":"S",
			"width":160,"height":8,
			"x":0,"y":136,
			"backgroundColor":{"_placeholder":"headerColor"},
			"zIndex":10
		}
	],
	"tilemaps":[{"tileWidth":16,"map":["BBBBBBBBBBBFFFFFASD"],"backgroundColor":{"_placeholder":"backgroundColor"}}],
	"code":[
		{
			"when":[{"as":"keyboard","attribute":"buttonA","if":[{"is":"hit"}]}],
			"then":[{"id":"A","playAudio":[{"_":{"_placeholder":"jumpPlayAudio"}}],"set":[{"gravityY":[{"_":0.3}],"speedY":[{"_":{"_placeholder":"jumpSize"}}]}]}]
		},
		{
			"when":[{"id":"A","if":[{"itsAttribute":"y","is":"<","_":0}]}],
			"then":[{"set":[{"y":[{"_":0}],"speedY":[{"_":0}]}]}]
		},
		{
			"when":[{"as":"scene","if":[{"itsAttribute":"timer","is":"%%","_":{"_placeholder":"difficulty"}}]}],
			"then":[
				{"as":"scene","set":[{"value1":[{"_":0}]}]},
				{
					"id":"D",
					"set":[{"y":[{"list":{"_placeholder":"holePositions"},"randomNumber":true}]}],
					"multiply":[{"y":[{"_":16}]}],
					"code":[{"then":[{"spawn":[{"ids":[{"_":"E"}]}]}]}]
				},
				{
					"code":[
						{
							"times":[{"_":8}],
							"then":[
								{
									"spawn":[{"ids":[{"_":"C"}],"at":[{"_":0}]}],
									"set":[{"y":[{"as":"scene","attribute":"value1"}]}],
									"code":[{
										"when":[{"if":[{"is":"collidingWith","id":"D"}]}],
										"then":[{"remove":true}]
									}]
								},
								{"as":"scene","sum":[{"value1":[{"_":16}]}]}
							]
						}
					]				
				}
			]
		},
		{
			"when":[{"id":"B"}],
			"then":[{
				"code":[
					{
						"when":[{"if":[{"itsAttribute":"x","is":"<","_":-16}]}],
						"then":[{"sum":[{"x":[{"_":176}]}]}]
					}
				]
			}]
		},
		{
			"when":[{"id":"F"}],
			"then":[{
				"code":[
					{
						"when":[{"if":[{"itsAttribute":"x","is":"<","_":-16}]}],
						"then":[
							{
								"randomize":true,
								"sum":[{
									"x":[{"list":[176,351],"randomNumber":true}]
								}],
								"set":[{
									"y":[{"list":[0,120],"randomNumber":true}]
								}]
							}
						]
					}
				]
			}]
		},
		{
			"when":[{"flags":"B"}],
			"then":[{
				"code":[
					{
						"when":[{"if":[{"itsAttribute":"x","is":"<","_":-16}]}],
						"then":[{"remove":true}]
					}
				]
			}]
		},{
			"when":[{"id":"E"}],
			"then":[{"code":[
				{
					"when":[{"if":[{"is":"collidingWith","id":"A"}]}],
					"then":[
						{"as":"scene","sum":[{"value0":[{"_":1}]}]},
						{"playAudio":[{"_":{"_placeholder":"pickPlayAudio"}}],"remove":true}
					]
				}
			]}]			
		},{
			"when":[{"id":"A","if":[{"is":"collidingWith","flags":"C"}]}],
			"then":[{"playAudio":[{"_":{"_placeholder":"failPlayAudio"}}],"runScene":[{"_":{"_placeholder":"runSceneGameOver"}}]}]
		},{
			"when":[{"as":"scene","attribute":"value0","if":[{"is":">=","_":{"_placeholder":"pickToGo"}}]}],
			"then":[{"runScene":[{"_":{"_placeholder":"runSceneComplete"}}]}]
		},
		{
			"then":[{
				"id":"S","set":[{"text":[{"as":"scene","attribute":"value0","prefix":{"_placeholder":"prefix"},"suffix":{"_placeholder":"suffix"}}]}]
			}]
		}
	]
}