{
	"_file":"games/shooting-game.json",
	"_replace":{
		"title":"V - SHOOT - Basic",
		"graphics":"graphics/shooting-star.png",
		"endingMusic":"songs/jinglebells-music.json",
		"endingSong":"songs/jinglebells-song.json",
		"endingSongTempo":5,
		"textTitle":"SUPER~~~~~~~~PLACE HERE~A MESSAGE FOR~THE TITLE~SCREEN!~~(C)2019 BY KESIEV",
		"textBriefing":"THIS IS THE~BRIEFING SCREEN.~~YOU CAN EXPLAIN~THE GAME RULES,~THE CONTROLS OR~TELL THE FIRST~PART OF YOUR~MESSAGE.~~HIT BUTTON TO~CONTINUE.",
		"textEnding":"THIS IS THE~ENDING SCREEN.~~YOU CAN THANK THE~PLAYER FOR~PLAYING BUT~YOU'LL MOSTLY WANT~TO SHOW YOUR~FINAL MESSAGE.~~REMEMBER TO ADD~YOUR NAME!",
		"goalPrefix":" BONUS: ",
		"titleBackgroundColor":0,
		"goalSuffix":"/10",
		"goalPickToGo":10,
		"stageBackgroundColor":1,
		"starColors":[2,3,4,5],
		"borderGraphicsY":2,
		"borderBackgroundColor":0,
		"starWidth":[1,2,3],
		"starHeight":[1,2,3],
		"starSpeed":[3,6],
		"scrollingSpeed":1,
		"playerGraphicsY":5,
		"bonusGraphicsY":7,
		"bonusBackgroundColor":0,
		"playerBulletGraphicsY":14,
		"enemyBulletGraphicsY":12,
		"enemyFlipYtoSpeedY":false,
		"enemyExplosionAudio":"sounds/effects/8bit-plip.json",
		"playerBulletAudio":"sounds/effects/8bit-laser.json",
		"enemyAnimationSpeed":0,
		"playerAnimationSpeed":0,
		"bonusSpeed":4,
		"enemyGraphicsY":6
	}
}